codexmcp/__init__.py
codexmcp/cli_backend.py
codexmcp/client.py
codexmcp/config.py
codexmcp/exceptions.py
codexmcp/logging_cfg.py
codexmcp/prompts.py
codexmcp/server.py
codexmcp/shared.py
codexmcp/tools.py
codexmcp/prompt_files/__init__.py
codexmcp/prompt_files/analyze_code_context.txt
codexmcp/prompt_files/assess_code_quality.txt
codexmcp/prompt_files/explain_code.txt
codexmcp/prompt_files/explain_code_for_audience.txt
codexmcp/prompt_files/generate_api_docs.txt
codexmcp/prompt_files/generate_code.txt
codexmcp/prompt_files/generate_docs.txt
codexmcp/prompt_files/generic_template.txt
codexmcp/prompt_files/interactive_code_generation.txt
codexmcp/prompt_files/migrate_code.txt
codexmcp/prompt_files/refactor_code.txt
codexmcp/prompt_files/search_codebase.txt
codexmcp/prompt_files/write_openai_agent.txt
codexmcp/prompt_files/write_tests.txt
codexmcp/templates/api_endpoint.txt
codexmcp-0.1.6.dist-info/licenses/LICENSE
codexmcp-0.1.6.dist-info/METADATA
codexmcp-0.1.6.dist-info/WHEEL
codexmcp-0.1.6.dist-info/entry_points.txt
codexmcp-0.1.6.dist-info/top_level.txt
codexmcp-0.1.6.dist-info/RECORD
