Metadata-Version: 2.4
Name: codexmcp
Version: 0.1.6
Summary: Minimal FastMCP server that wraps the OpenAI Codex CLI
Author-email: Tomas Cupr <work@tomcupr.com>
Project-URL: Homepage, https://github.com/tomascupr/codexmcp
Requires-Python: >=3.10
License-File: LICENSE
Requires-Dist: fastmcp
Requires-Dist: python-dotenv
Requires-Dist: rich
Provides-Extra: test
Requires-Dist: pytest>=7.0.0; extra == "test"
Requires-Dist: pytest-asyncio>=0.18.0; extra == "test"
Requires-Dist: pytest-cov>=3.0.0; extra == "test"
Provides-Extra: openai
Requires-Dist: openai>=1.3.0; extra == "openai"
Dynamic: license-file
